{"name":"Memorypuzzle","tagline":"Memory Puzzle game developed using Pygame.","body":"Memory puzzle is a simple memory puzzle game where you join two matching pieces and when all pieces are matched, you win. This is adopted from the game written by Al Sweigart <al@inventwithpython.com>.\r\n\r\nThis version has 3 levels, Easy, Medium and Hard.\r\n\r\n### Game Opening\r\n\r\n![Game Opening](https://dl.dropbox.com/s/521qoblj6k0nte8/memorypuzzle_opening.png)\r\n\r\n\r\n### Easy Level\r\n\r\n![Easy Level](https://dl.dropbox.com/s/3k8tee7hrixy4ak/memorypuzzle_easy.png)\r\n\r\n### Medium Level\r\n\r\n![Medium Level](https://dl.dropbox.com/s/g70aj08r4sls78r/memorypuzzle_medium.png)\r\n\r\n### Hard Level\r\n\r\n![Hard Level](https://dl.dropbox.com/s/tmbwv33y52hxyql/memorypuzzle_hard.png)\r\n\r\n### Game Source\r\n\r\n`https://github.com/uthcode/memorypuzzle/`\r\n\r\nAim of this game was also to write modular reusable code, with the aim of longevity. The code has good test coverage too. \r\n\r\n### Author\r\n\r\nSenthil Kumaran <senthil@uthcode.com>","google":"","note":"Don't delete this file! It's used internally to help with page regeneration."}